coactive/__init__.py
coactive/client.py
coactive/core/__init__.py
coactive/core/api_error.py
coactive/core/client_wrapper.py
coactive/core/datetime_utils.py
coactive/core/jsonable_encoder.py
coactive/core/remove_none_from_dict.py
coactive/environment.py
coactive/errors/__init__.py
coactive/errors/bad_request_error.py
coactive/errors/not_found_error.py
coactive/errors/unprocessable_entity_error.py
coactive/py.typed
coactive/resources/__init__.py
coactive/resources/asset/__init__.py
coactive/resources/asset/client.py
coactive/resources/asset/types/__init__.py
coactive/resources/asset/types/image_or_keyframe_detail.py
coactive/resources/classification/__init__.py
coactive/resources/classification/client.py
coactive/resources/concept/__init__.py
coactive/resources/concept/client.py
coactive/resources/credentials/__init__.py
coactive/resources/credentials/client.py
coactive/resources/dataset/__init__.py
coactive/resources/dataset/client.py
coactive/resources/dynamic_tags/__init__.py
coactive/resources/dynamic_tags/client.py
coactive/resources/query/__init__.py
coactive/resources/query/client.py
coactive/resources/search/__init__.py
coactive/resources/search/client.py
coactive/types/__init__.py
coactive/types/add_assets_confirmation.py
coactive/types/add_image_request.py
coactive/types/add_video_request.py
coactive/types/added_image.py
coactive/types/added_video.py
coactive/types/app_shared_v_0_schema_shot.py
coactive/types/asset.py
coactive/types/asset_type_enum.py
coactive/types/audio_segment.py
coactive/types/basic_description.py
coactive/types/candidates_to_label.py
coactive/types/category_response.py
coactive/types/classification.py
coactive/types/classification_score.py
coactive/types/concept.py
coactive/types/concept_label.py
coactive/types/concept_label_enum.py
coactive/types/concept_label_request.py
coactive/types/concept_prediction_response.py
coactive/types/credentials.py
coactive/types/credentials_validation.py
coactive/types/dataset.py
coactive-1.0.27.dist-info/METADATA
coactive-1.0.27.dist-info/WHEEL
coactive-1.0.27.dist-info/RECORD
